vibelint/VIBECHECKER.txt
vibelint/__init__.py
vibelint/ascii.py
vibelint/cli.py
vibelint/config.py
vibelint/discovery.py
vibelint/error_codes.py
vibelint/lint.py
vibelint/namespace.py
vibelint/report.py
vibelint/results.py
vibelint/snapshot.py
vibelint/utils.py
vibelint/validators/__init__.py
vibelint/validators/docstring.py
vibelint/validators/encoding.py
vibelint/validators/exports.py
vibelint/validators/shebang.py
vibelint-0.1.2.dist-info/licenses/LICENSE
vibelint-0.1.2.dist-info/METADATA
vibelint-0.1.2.dist-info/WHEEL
vibelint-0.1.2.dist-info/entry_points.txt
vibelint-0.1.2.dist-info/top_level.txt
vibelint-0.1.2.dist-info/RECORD
