Metadata-Version: 2.4
Name: vibelint
Version: 0.1.2
Summary: Suite of tools to enhance the vibe coding process.
Author-email: Mithran Mohanraj <mithran.mohanraj@gmail.com>
License: MIT
Project-URL: Homepage, https://github.com/mithranm/vibelint
Project-URL: Bug Tracker, https://github.com/mithranm/vibelint/issues
Classifier: Development Status :: 3 - Alpha
Classifier: Environment :: Console
Classifier: Intended Audience :: Developers
Classifier: License :: OSI Approved :: MIT License
Classifier: Programming Language :: Python :: 3
Classifier: Programming Language :: Python :: 3.10
Classifier: Programming Language :: Python :: 3.11
Classifier: Programming Language :: Python :: 3.12
Classifier: Topic :: Software Development :: Quality Assurance
Requires-Python: >=3.10
License-File: LICENSE
Requires-Dist: click>=8.1.0
Requires-Dist: tomli>=2.0.0; python_version < "3.11"
Requires-Dist: tomli-w
Requires-Dist: colorama>=0.4.0
Requires-Dist: rich>=12.0.0
Requires-Dist: libcst
Dynamic: license-file
